CHANGES.txt
COPYRIGHT.txt
LICENSE.txt
MANIFEST.in
README.txt
bootstrap.py
buildout.cfg
setup.py
src/tranchitella/__init__.py
src/tranchitella.recipe.i18n.egg-info/PKG-INFO
src/tranchitella.recipe.i18n.egg-info/SOURCES.txt
src/tranchitella.recipe.i18n.egg-info/dependency_links.txt
src/tranchitella.recipe.i18n.egg-info/entry_points.txt
src/tranchitella.recipe.i18n.egg-info/namespace_packages.txt
src/tranchitella.recipe.i18n.egg-info/not-zip-safe
src/tranchitella.recipe.i18n.egg-info/requires.txt
src/tranchitella.recipe.i18n.egg-info/top_level.txt
src/tranchitella/recipe/__init__.py
src/tranchitella/recipe/i18n/__init__.py
src/tranchitella/recipe/i18n/i18ncompile.py
src/tranchitella/recipe/i18n/i18nextract.py
src/tranchitella/recipe/i18n/i18nmerge.py
src/tranchitella/recipe/i18n/i18nstats.py
src/tranchitella/recipe/i18n/pygettext.py
src/tranchitella/recipe/i18n/tests.py