Metadata-Version: 1.0
Name: tranchitella.recipe.i18n
Version: 0.5
Summary: Buildout recipe to extract and manage po files
Home-page: http://pypi.python.org/pypi/tranchitella.recipe.i18n
Author: Tranchitella Kft.
Author-email: info@tranchitella.eu
License: GPL 2
Platform: UNKNOWN
Classifier: Framework :: Buildout
Classifier: Intended Audience :: Developers
Classifier: Intended Audience :: System Administrators
Classifier: License :: OSI Approved :: GNU General Public License (GPL)
Classifier: Programming Language :: Python
